securetar/__init__.py
securetar-2025.12.0.dist-info/licenses/LICENSE
securetar-2025.12.0.dist-info/METADATA
securetar-2025.12.0.dist-info/WHEEL
securetar-2025.12.0.dist-info/top_level.txt
securetar-2025.12.0.dist-info/RECORD
