Metadata-Version: 2.4
Name: securetar
Version: 2025.12.0
Summary: Python module to handle tarfile backups.
Author-email: Pascal Vizeli <pvizeli@syshack.ch>
License: Apache-2.0
Project-URL: Homepage, https://github.com/pvizeli/securetar
Classifier: Intended Audience :: Developers
Classifier: Operating System :: OS Independent
Classifier: Programming Language :: Python
Classifier: Programming Language :: Python :: 3
Classifier: Topic :: Software Development :: Libraries :: Python Modules
Requires-Python: >=3.11.0
License-File: LICENSE
Requires-Dist: cryptography
Dynamic: license-file
